PySyntenyViz/__init__.py
PySyntenyViz/change_gbk_origin.py
PySyntenyViz/cli.py
PySyntenyViz/gbk_rc.py
PySyntenyViz/reorder_gbk.py
PySyntenyViz/synteny_viz.py
pysyntenyviz-0.2.1.dist-info/licenses/LICENSE
pysyntenyviz-0.2.1.dist-info/METADATA
pysyntenyviz-0.2.1.dist-info/WHEEL
pysyntenyviz-0.2.1.dist-info/entry_points.txt
pysyntenyviz-0.2.1.dist-info/top_level.txt
pysyntenyviz-0.2.1.dist-info/RECORD
