Metadata-Version: 2.4
Name: PySyntenyViz
Version: 0.2.1
Summary: A CLI to create and annotate synteny plots for microbial genomes or plasmids. It uses GenBank files as input and creates alignment on the fly. It provides additional tools to edit the GenBank files to customize the synteny plot.
Author-email: Arafat Rahman <ac.arafat@gmail.com>
Project-URL: homepage, https://github.com/acarafat/PySyntenyViz
Project-URL: Repository, https://github.com/acarafat/PySyntenyViz
Requires-Python: >=3.6
License-File: LICENSE
Requires-Dist: biopython
Requires-Dist: argparse
Requires-Dist: pandas
Requires-Dist: pygenomeviz
Dynamic: license-file
